chaparral/__init__.py
chaparral/agents/BaseAgent.py
chaparral/agents/agentsNN.py
chaparral/agents/deepQ.py
chaparral/agents/networks.py
chaparral/data/objetos_mapa/objetos_mapa_objetos_api_v1.ndjson
chaparral/data/objetos_mapa/rutas.json
chaparral/main/cargar_inventario.py
chaparral/main/cargar_mapa.py
chaparral/main/crear_aristas.py
chaparral/main/gmap_geolocalizaciones.py
chaparral/main/manual_geolocalizationes.py
chaparral/mapa/__init__.py
chaparral/mapa/convenciones.py
chaparral/mapa/espacio_rutas.py
chaparral/mapa/espacio_utils.py
chaparral/mapa/explore_map.py
chaparral/mapa/map_objects.py
chaparral/mapa/rutas.py
chaparral/modelos/ambiente.py
chaparral/modelos/baseline.py
chaparral/modelos/busqueda.py
chaparral/modelos/clases.py
chaparral/modelos/clases_v0.py
chaparral/modelos/constantes copy.py
chaparral/modelos/constantes.py
chaparral/modelos/entorno.py
chaparral/modelos/entorno_v0.py
chaparral/modelos/modelo_utils.py
chaparral/utils/__init__.py
chaparral/utils/interaction.py
chaparral/utils/interpreters.py
chaparral/utils/performer.py
chaparral/utils/plot_utils.py
Chaparral-0.0.14.dist-info/LICENSE
Chaparral-0.0.14.dist-info/METADATA
Chaparral-0.0.14.dist-info/WHEEL
Chaparral-0.0.14.dist-info/top_level.txt
Chaparral-0.0.14.dist-info/RECORD
